{
  "groups": [
    {
      "name": "蔚来",
      "keywords": [
        "蔚来",
        "换电",
        "李斌",
        "乐道",
        "萤火虫",
        "租电",
        "baas",
        "沈斐",
        "秦力洪",
        "世界模型",
        "任少卿",
        "蔚能",
        "ES6",
        "ES7",
        "ES8",
        "ES9",
        "ET5",
        "ET5T",
        "ET7",
        "EC6",
        "EC7",
        "ET9",
        "L60",
        "L90",
        "L80",
        "神玑",
        "Sky",
        "NIO"
      ],
      "created_at": "2026-06-20",
      "note": ""
    }
  ],
  "recent": [
    "蔚来, 换电, 李斌, 乐道, 萤火虫, 租电, baas, 沈斐, 秦力洪, 世界模型, 任少卿, 蔚能, ES6, ES7, ES8, ES9, ET5, ET5T, ET7, EC6, EC7, ET9, L60, L90, L80, 神玑, Sky, NIO",
    "蔚来, 换电, 李斌, 乐道, 萤火虫, 租电, baas, 沈斐, 秦力洪, 世界模型, 任少卿, 蔚能, ES, ET, EC, 神玑, Sky, NIO, 蔚, 阿来",
    "蔚来, 换电, 李斌, 乐道, 萤火虫, 租电, baas, 沈斐, 秦力洪, 世界模型, 任少卿, 蔚能, ES, ET, EC, 神玑, Sky, NIO, 蔚",
    "蔚来、换电、李斌、乐道、萤火虫、租电、baas、沈斐、秦力洪、世界模型、任少卿、蔚能、 ES、ET、EC、神玑、Sky、NIO、蔚",
    "蔚来、换电、李斌、乐道、萤火虫、租电、baas、沈斐、秦力洪、世界模型、任少卿、蔚能、 ES、ET、EC、神玑、Sky、NIO"
  ]
}